uvp/__init__.py
uvp-0.0.2.dist-info/WHEEL
uvp-0.0.2.dist-info/entry_points.txt
uvp-0.0.2.dist-info/METADATA
uvp-0.0.2.dist-info/RECORD
