Metadata-Version: 2.3
Name: uvp
Version: 0.0.2
Summary: Python Repo Management
Author: djestaz
Author-email: djestaz <djestacom@gmail.com>
Classifier: Programming Language :: Python :: 3
Classifier: License :: OSI Approved :: MIT License
Classifier: Operating System :: OS Independent
Requires-Python: >=3.14
